plotpy/__init__.py
plotpy/_scaler.cp39-win32.pyd
plotpy/config.py
plotpy/constants.py
plotpy/coords.py
plotpy/events.py
plotpy/histogram2d.cp39-win32.pyd
plotpy/io.py
plotpy/lutrange.py
plotpy/mandelbrot.cp39-win32.pyd
plotpy/pyplot.py
plotpy/builder/__init__.py
plotpy/builder/annotation.py
plotpy/builder/curvemarker.py
plotpy/builder/image.py
plotpy/builder/label.py
plotpy/builder/plot.py
plotpy/builder/shape.py
plotpy/data/colormaps_default.json
plotpy/data/icons/apply.png
plotpy/data/icons/arredit.png
plotpy/data/icons/arrow_down.png
plotpy/data/icons/arrow_up.png
plotpy/data/icons/autorefresh.png
plotpy/data/icons/autoscale.png
plotpy/data/icons/axes.png
plotpy/data/icons/busy.png
plotpy/data/icons/cell_edit.png
plotpy/data/icons/center.png
plotpy/data/icons/cmap_edit.png
plotpy/data/icons/contrast.png
plotpy/data/icons/copy.png
plotpy/data/icons/copytoclipboard.png
plotpy/data/icons/csapplylut.png
plotpy/data/icons/csautoscale.png
plotpy/data/icons/csection.png
plotpy/data/icons/csection_a.png
plotpy/data/icons/csection_line.png
plotpy/data/icons/csection_oblique.png
plotpy/data/icons/csperimage.png
plotpy/data/icons/curve_downsample.png
plotpy/data/icons/delete.png
plotpy/data/icons/edit.png
plotpy/data/icons/edit_point_selection.png
plotpy/data/icons/eliminate_outliers.png
plotpy/data/icons/eraser.png
plotpy/data/icons/exit.png
plotpy/data/icons/expander_down.png
plotpy/data/icons/expander_right.png
plotpy/data/icons/export.png
plotpy/data/icons/file.png
plotpy/data/icons/fileclose.png
plotpy/data/icons/fileimport.png
plotpy/data/icons/filenew.png
plotpy/data/icons/fileopen.png
plotpy/data/icons/filesave.png
plotpy/data/icons/filesaveas.png
plotpy/data/icons/font.png
plotpy/data/icons/full_range.png
plotpy/data/icons/funct.png
plotpy/data/icons/hcursor.png
plotpy/data/icons/hflip.png
plotpy/data/icons/imagestats.png
plotpy/data/icons/item_list.png
plotpy/data/icons/magnifier.png
plotpy/data/icons/max.png
plotpy/data/icons/min.png
plotpy/data/icons/move.png
plotpy-2.8.3.dist-info/licenses/LICENSE
plotpy-2.8.3.dist-info/METADATA
plotpy-2.8.3.dist-info/WHEEL
plotpy-2.8.3.dist-info/entry_points.txt
plotpy-2.8.3.dist-info/top_level.txt
plotpy-2.8.3.dist-info/RECORD
