Metadata-Version: 2.4
Name: PlotPy
Version: 2.8.3
Summary: Curve and image plotting tools for Python/Qt applications
Author-email: Codra <p.raybaut@codra.fr>
License: BSD 3-Clause License
Project-URL: Homepage, https://github.com/PlotPyStack/plotpy/
Project-URL: Documentation, https://plotpy.readthedocs.io/en/latest/
Classifier: Development Status :: 5 - Production/Stable
Classifier: Intended Audience :: Developers
Classifier: Intended Audience :: Education
Classifier: Intended Audience :: Science/Research
Classifier: Operating System :: MacOS :: MacOS X
Classifier: Operating System :: Microsoft :: Windows :: Windows 7
Classifier: Operating System :: Microsoft :: Windows :: Windows 8
Classifier: Operating System :: Microsoft :: Windows :: Windows 10
Classifier: Operating System :: Microsoft :: Windows :: Windows 11
Classifier: Operating System :: POSIX :: Linux
Classifier: Programming Language :: Python :: 3.9
Classifier: Programming Language :: Python :: 3.10
Classifier: Programming Language :: Python :: 3.11
Classifier: Programming Language :: Python :: 3.12
Classifier: Programming Language :: Python :: 3.13
Classifier: Topic :: Scientific/Engineering
Classifier: Topic :: Scientific/Engineering :: Image Processing
Classifier: Topic :: Scientific/Engineering :: Human Machine Interfaces
Classifier: Topic :: Scientific/Engineering :: Visualization
Classifier: Topic :: Software Development :: Libraries :: Python Modules
Classifier: Topic :: Software Development :: User Interfaces
Classifier: Topic :: Software Development :: Widget Sets
Classifier: Topic :: Utilities
Requires-Python: <4,>=3.9
License-File: LICENSE
Requires-Dist: guidata>=3.13
Requires-Dist: PythonQwt>=0.15
Requires-Dist: numpy>=1.22
Requires-Dist: SciPy>=1.7.3
Requires-Dist: scikit-image>=0.19
Requires-Dist: Pillow
Requires-Dist: tifffile
Provides-Extra: qt
Requires-Dist: PyQt5>5.15.5; extra == "qt"
Provides-Extra: dev
Requires-Dist: build; extra == "dev"
Requires-Dist: babel; extra == "dev"
Requires-Dist: Coverage; extra == "dev"
Requires-Dist: Cython>=3.0; extra == "dev"
Requires-Dist: pylint; extra == "dev"
Requires-Dist: ruff; extra == "dev"
Requires-Dist: pre-commit; extra == "dev"
Provides-Extra: doc
Requires-Dist: sphinx; extra == "doc"
Requires-Dist: myst_parser; extra == "doc"
Requires-Dist: sphinx-copybutton; extra == "doc"
Requires-Dist: sphinx_qt_documentation; extra == "doc"
Requires-Dist: python-docs-theme; extra == "doc"
Provides-Extra: test
Requires-Dist: pytest; extra == "test"
Requires-Dist: pytest-xvfb; extra == "test"
Dynamic: license-file
